virgo/.gitignore
virgo/__init__.py
virgo/graph.py
virgo/internal.py
virgo/load.py
virgo/parse.py
virgo/preprocess.py
pyvirgo-0.2.0.dist-info/LICENSE
pyvirgo-0.2.0.dist-info/WHEEL
pyvirgo-0.2.0.dist-info/METADATA
pyvirgo-0.2.0.dist-info/RECORD
